{
    "products": [
        {
            "tag": ["Nuevos"],
            "wishlist": true,
            "wishlistLink": "https://example.com/wishlist-products/product-new-2",
            "wishlistAdded": true,
            "img": "https://media.ulta.com/i/ulta/2627058?w=400&$ProductCardNeutralBGLight$&fmt=auto",
            "brand": "IT Brushes For ULTA",
            "name": "IT Brushes For ULTA x Wicked Edición limitada Blush & Base de maquillaje texto para overflow test",
            "ranking": 85,
            "rankingComment": 150,
            "normalPrice": "1,171.17",
            "specialPrice": "999.50",
            "linkPdp": "https://example.com/products/product-new-1",
            "addToCartLink": "https://example.com/cart/add/product-new-1",
            "sku": "SKU-N-001",
            "colorVariation": 3,
            "badge": "https://author-p34631-e1321407.adobeaemcloud.com/content/dam/learning-wysiwyg-con-edge-delivery-services/allure_badge.png",
            "promo": "Compra 2, lleva 1 gratis"
        },
        {
            "tag": ["Nuevos"],
            "wishlist": false,
            "wishlistLink": false,
            "wishlistAdded": false,
            "img": "https://media.ulta.com/i/ulta/2580264?w=400&$ProductCardNeutralBGLight$&fmt=auto",
            "brand": "r.e.m. beauty",
            "name": "r.e.m. beauty x Wicked Set de maquillaje",
            "ranking": 90,
            "rankingComment": 200,
            "normalPrice": "150.00",
            "specialPrice": "130.00",
            "linkPdp": "https://example.com/products/product-new-2",
            "addToCartLink": "https://example.com/cart/add/product-new-2",
            "sku": "SKU-N-002",
            "colorVariation": 0,
            "badge": "https://author-p34631-e1321407.adobeaemcloud.com/content/dam/learning-wysiwyg-con-edge-delivery-services/allure_badge.png",
            "promo": ""
        },
        {
            "tag": ["Nuevos"],
            "wishlist": true,
            "wishlistLink": "https://example.com/wishlist-products/product-new-2",
            "wishlistAdded": false,
            "img": "https://media.ulta.com/i/ulta/2637683?w=400&$ProductCardNeutralBGLight$&fmt=auto",
            "brand": "Brand C",
            "name": "Producto Nuevo 3",
            "ranking": 75,
            "rankingComment": 80,
            "normalPrice": "100.00",
            "specialPrice": "",
            "linkPdp": "https://example.com/products/product-new-3",
            "addToCartLink": "https://example.com/cart/add/product-new-3",
            "sku": "SKU-N-003",
            "colorVariation": 4,
            "badge": "",
            "promo": ""
        },
        {
            "tag": ["Nuevos"],
            "wishlist": true,
            "wishlistLink": "https://example.com/wishlist-products/product-new-2",
            "wishlistAdded": true,
            "img": "https://media.ulta.com/i/ulta/2531897?w=400&$ProductCardNeutralBGLight$&fmt=auto",
            "brand": "Brand D",
            "name": "Producto Nuevo 4",
            "ranking": 80,
            "rankingComment": 110,
            "normalPrice": "130.00",
            "specialPrice": "",
            "linkPdp": "https://example.com/products/product-new-4",
            "addToCartLink": "https://example.com/cart/add/product-new-4",
            "sku": "SKU-N-004",
            "colorVariation": 0,
            "badge": "",
            "promo": ""
        },
        {
            "tag": ["Nuevos"],
            "wishlist": true,
            "wishlistLink": "https://example.com/wishlist-products/product-new-2",
            "wishlistAdded": false,
            "img": "https://media.ulta.com/i/ulta/2597684?w=400&$ProductCardNeutralBGLight$&fmt=auto",
            "brand": "Brand E",
            "name": "Producto Nuevo 5",
            "ranking": 95,
            "rankingComment": 250,
            "normalPrice": "200.00",
            "specialPrice": "180.00",
            "linkPdp": "https://example.com/products/product-new-5",
            "addToCartLink": "https://example.com/cart/add/product-new-5",
            "sku": "SKU-N-005",
            "colorVariation": 0,
            "badge": "https://author-p34631-e1321407.adobeaemcloud.com/content/dam/learning-wysiwyg-con-edge-delivery-services/allure_badge.png",
            "promo": ""
        },
        {
            "tag": ["Nuevos"],
            "wishlist": true,
            "wishlistLink": "https://example.com/wishlist-products/product-new-2",
            "wishlistAdded": false,
            "img": "https://media.ulta.com/i/ulta/2622680?w=400&$ProductCardNeutralBGLight$&fmt=auto",
            "brand": "Brand F",
            "name": "Producto Nuevo 6",
            "ranking": 70,
            "rankingComment": 60,
            "normalPrice": "90.00",
            "specialPrice": "80.00",
            "linkPdp": "https://example.com/products/product-new-6",
            "addToCartLink": "https://example.com/cart/add/product-new-6",
            "sku": "SKU-N-006",
            "colorVariation": 2,
            "badge": "https://author-p34631-e1321407.adobeaemcloud.com/content/dam/learning-wysiwyg-con-edge-delivery-services/allure_badge.png",
            "promo": "Compra 2, lleva 1 gratis"
        },
        {
            "tag": ["Exclusivo"],
            "wishlist": true,
            "wishlistLink": "https://example.com/wishlist-products/product-new-2",
            "wishlistAdded": false,
            "img": "https://media.ulta.com/i/ulta/2261902?w=400&$ProductCardNeutralBGLight$&fmt=auto",
            "brand": "Brand G",
            "name": "Producto Exclusivo 1",
            "ranking": 88,
            "rankingComment": 175,
            "normalPrice": "160.00",
            "specialPrice": "140.00",
            "linkPdp": "https://example.com/products/product-exclusive-1",
            "addToCartLink": "https://example.com/cart/add/product-exclusive-1",
            "sku": "SKU-E-001",
            "colorVariation": 2,
            "badge": "https://author-p34631-e1321407.adobeaemcloud.com/content/dam/learning-wysiwyg-con-edge-delivery-services/allure_badge.png",
            "promo": "Compra 2, lleva 1 gratis"
        },
        {
            "tag": ["Exclusivo"],
            "wishlist": true,
            "wishlistLink": "https://example.com/wishlist-products/product-new-2",
            "wishlistAdded": true,
            "img": "https://media.ulta.com/i/ulta/2543119?w=400&$ProductCardNeutralBGLight$&fmt=auto",
            "brand": "Brand H",
            "name": "Producto Exclusivo 2",
            "ranking": 92,
            "rankingComment": 210,
            "normalPrice": "170.00",
            "specialPrice": "150.00",
            "linkPdp": "https://example.com/products/product-exclusive-2",
            "addToCartLink": "https://example.com/cart/add/product-exclusive-2",
            "sku": "SKU-E-002",
            "colorVariation": 0,
            "badge": "",
            "promo": ""
        },
        {
            "tag": ["Exclusivo"],
            "wishlist": true,
            "wishlistLink": "https://example.com/wishlist-products/product-new-2",
            "wishlistAdded": false,
            "img": "https://media.ulta.com/i/ulta/2612032?w=400&$ProductCardNeutralBGLight$&fmt=auto",
            "brand": "Brand I",
            "name": "Producto Exclusivo 3",
            "ranking": 80,
            "rankingComment": 130,
            "normalPrice": "140.00",
            "specialPrice": "125.00",
            "linkPdp": "https://example.com/products/product-exclusive-3",
            "addToCartLink": "https://example.com/cart/add/product-exclusive-3",
            "sku": "SKU-E-003",
            "colorVariation": 1,
            "badge": "https://author-p34631-e1321407.adobeaemcloud.com/content/dam/learning-wysiwyg-con-edge-delivery-services/allure_badge.png",
            "promo": ""
        },
        {
            "tag": ["Exclusivo"],
            "wishlist": true,
            "wishlistLink": "https://example.com/wishlist-products/product-new-2",
            "wishlistAdded": false,
            "img": "https://media.ulta.com/i/ulta/2611722?w=400&$ProductCardNeutralBGLight$&fmt=auto",
            "brand": "Brand J",
            "name": "Producto Exclusivo 4",
            "ranking": 85,
            "rankingComment": 160,
            "normalPrice": "155.00",
            "specialPrice": "135.00",
            "linkPdp": "https://example.com/products/product-exclusive-4",
            "addToCartLink": "https://example.com/cart/add/product-exclusive-4",
            "sku": "SKU-E-004",
            "colorVariation": 2,
            "badge": "",
            "promo": ""
        },
        {
            "tag": ["Exclusivo"],
            "wishlist": true,
            "wishlistLink": "https://example.com/wishlist-products/product-new-2",
            "wishlistAdded": false,
            "img": "https://media.ulta.com/i/ulta/2620126?w=400&$ProductCardNeutralBGLight$&fmt=auto",
            "brand": "Brand K",
            "name": "Producto Exclusivo 5",
            "ranking": 78,
            "rankingComment": 140,
            "normalPrice": "145.00",
            "specialPrice": "130.00",
            "linkPdp": "https://example.com/products/product-exclusive-5",
            "addToCartLink": "https://example.com/cart/add/product-exclusive-5",
            "sku": "SKU-E-005",
            "colorVariation": 3,
            "badge": "",
            "promo": ""
        },
        {
            "tag": ["Exclusivo"],
            "wishlist": true,
            "wishlistLink": "https://example.com/wishlist-products/product-new-2",
            "wishlistAdded": true,
            "img": "https://media.ulta.com/i/ulta/2635146?w=400&$ProductCardNeutralBGLight$&fmt=auto",
            "brand": "Brand L",
            "name": "Producto Exclusivo 6",
            "ranking": 90,
            "rankingComment": 190,
            "normalPrice": "165.00",
            "specialPrice": "145.00",
            "linkPdp": "https://example.com/products/product-exclusive-6",
            "addToCartLink": "https://example.com/cart/add/product-exclusive-6",
            "sku": "SKU-E-006",
            "colorVariation": 2,
            "badge": "",
            "promo": ""
        },
        {
            "tag": ["Exclusivo", "Cruelty Free"],
            "wishlist": true,
            "wishlistLink": "https://example.com/wishlist-products/product-new-2",
            "wishlistAdded": false,
            "img": "https://media.ulta.com/i/ulta/2625997?w=400&$ProductCardNeutralBGLight$&fmt=auto",
            "brand": "Brand M",
            "name": "Producto Exclusivo CF 1",
            "ranking": 93,
            "rankingComment": 220,
            "normalPrice": "180.00",
            "specialPrice": "160.00",
            "linkPdp": "https://example.com/products/product-exclusive-cf-1",
            "addToCartLink": "https://example.com/cart/add/product-exclusive-cf-1",
            "sku": "SKU-ECF-001",
            "colorVariation": 3,
            "badge": "",
            "promo": "Compra 2, lleva 1 gratis"
        },
        {
            "tag": ["Exclusivo", "Cruelty Free"],
            "wishlist": true,
            "wishlistLink": "https://example.com/wishlist-products/product-new-2",
            "wishlistAdded": false,
            "img": "https://media.ulta.com/i/ulta/2634416?w=400&$ProductCardNeutralBGLight$&fmt=auto",
            "brand": "Brand N",
            "name": "Producto Exclusivo CF 2",
            "ranking": 87,
            "rankingComment": 180,
            "normalPrice": "175.00",
            "specialPrice": "155.00",
            "linkPdp": "https://example.com/products/product-exclusive-cf-2",
            "addToCartLink": "https://example.com/cart/add/product-exclusive-cf-2",
            "sku": "SKU-ECF-002",
            "colorVariation": 2,
            "badge": "",
            "promo": ""
        },
        {
            "tag": ["Exclusivo", "Cruelty Free"],
            "wishlist": true,
            "wishlistLink": "https://example.com/wishlist-products/product-new-2",
            "wishlistAdded": false,
            "img": "https://media.ulta.com/i/ulta/2635120?w=400&$ProductCardNeutralBGLight$&fmt=auto",
            "brand": "Brand O",
            "name": "Producto Exclusivo CF 3",
            "ranking": 82,
            "rankingComment": 140,
            "normalPrice": "160.00",
            "specialPrice": "140.00",
            "linkPdp": "https://example.com/products/product-exclusive-cf-3",
            "addToCartLink": "https://example.com/cart/add/product-exclusive-cf-3",
            "sku": "SKU-ECF-003",
            "colorVariation": 1,
            "badge": "https://author-p34631-e1321407.adobeaemcloud.com/content/dam/learning-wysiwyg-con-edge-delivery-services/allure_badge.png",
            "promo": ""
        },
        {
            "tag": ["Exclusivo", "Cruelty Free"],
            "wishlist": true,
            "wishlistLink": "https://example.com/wishlist-products/product-new-2",
            "wishlistAdded": false,
            "img": "https://media.ulta.com/i/ulta/2611761?w=400&$ProductCardNeutralBGLight$&fmt=auto",
            "brand": "Brand P",
            "name": "Producto Exclusivo CF 4",
            "ranking": 88,
            "rankingComment": 170,
            "normalPrice": "170.00",
            "specialPrice": "150.00",
            "linkPdp": "https://example.com/products/product-exclusive-cf-4",
            "addToCartLink": "https://example.com/cart/add/product-exclusive-cf-4",
            "sku": "SKU-ECF-004",
            "colorVariation": 2,
            "badge": "",
            "promo": "Compra 2, lleva 1 gratis"
        },
        {
            "tag": ["Exclusivo", "Cruelty Free"],
            "wishlist": true,
            "wishlistLink": "https://example.com/wishlist-products/product-new-2",
            "wishlistAdded": false,
            "img": "https://media.ulta.com/i/ulta/2631717?w=400&$ProductCardNeutralBGLight$&fmt=auto",
            "brand": "Brand Q",
            "name": "Producto Exclusivo CF 5",
            "ranking": 91,
            "rankingComment": 210,
            "normalPrice": "185.00",
            "specialPrice": "165.00",
            "linkPdp": "https://example.com/products/product-exclusive-cf-5",
            "addToCartLink": "https://example.com/cart/add/product-exclusive-cf-5",
            "sku": "SKU-ECF-005",
            "colorVariation": 0,
            "badge": "",
            "promo": "Compra 2, lleva 1 gratis"
        },
        {
            "tag": ["Exclusivo", "Cruelty Free"],
            "wishlist": true,
            "wishlistLink": "https://example.com/wishlist-products/product-new-2",
            "wishlistAdded": false,
            "img": "https://media.ulta.com/i/ulta/2609293?w=400&$ProductCardNeutralBGLight$&fmt=auto",
            "brand": "Brand R",
            "name": "Producto Exclusivo CF 6",
            "ranking": 86,
            "rankingComment": 160,
            "normalPrice": "175.00",
            "specialPrice": "155.00",
            "linkPdp": "https://example.com/products/product-exclusive-cf-6",
            "addToCartLink": "https://example.com/cart/add/product-exclusive-cf-6",
            "sku": "SKU-ECF-006",
            "colorVariation": 2,
            "badge": "",
            "promo": "Compra 2, lleva 1 gratis"
        }
    ]
}
